pynenc_rabbitmq/__init__.py
pynenc_rabbitmq/builder.py
pynenc_rabbitmq/broker/__init__.py
pynenc_rabbitmq/broker/rabbitmq_broker.py
pynenc_rabbitmq/conf/__init__.py
pynenc_rabbitmq/conf/config_broker.py
pynenc_rabbitmq/conf/config_rabbitmq.py
pynenc_rabbitmq/util/__init__.py
pynenc_rabbitmq/util/rabbitmq_client.py
pynenc_rabbitmq/util/rabbitmq_conn_mng.py
pynenc_rabbitmq/util/rabbitmq_queue.py
pynenc_rabbitmq/util/rabbitmq_queue_mng.py
pynenc_rabbitmq-0.1.4.dist-info/METADATA
pynenc_rabbitmq-0.1.4.dist-info/WHEEL
pynenc_rabbitmq-0.1.4.dist-info/entry_points.txt
pynenc_rabbitmq-0.1.4.dist-info/licenses/LICENSE
pynenc_rabbitmq-0.1.4.dist-info/RECORD
